CHANGES.rst
LICENSE
MANIFEST.in
README.rst
setup.cfg
setup.py
tox.ini
docs/CHANGES.rst
docs/README.rst
docs/advanced_topics.rst
docs/changelog.rst
docs/conf.py
docs/faq.rst
docs/getting_started.rst
docs/index-py4j-web.rst
docs/index.rst
docs/py4j_java_gateway.rst
docs/py4j_signals.rst
docs/_static/.keep
docs/_templates/.keep
src/jt/__init__.py
src/jt/py4j.cfg
src/jt/py4j/__about__.py
src/jt/py4j/__config__.py
src/jt/py4j/__init__.py
src/jt/py4j/version.py
src/jt/py4j/_java/__init__.py
src/jt/py4j/_java/class2py.py
src/jtypes.py4j.egg-info/PKG-INFO
src/jtypes.py4j.egg-info/SOURCES.txt
src/jtypes.py4j.egg-info/dependency_links.txt
src/jtypes.py4j.egg-info/namespace_packages.txt
src/jtypes.py4j.egg-info/requires.txt
src/jtypes.py4j.egg-info/top_level.txt
src/jtypes.py4j.egg-info/zip-safe
tests/__init__.py
tests/__main__.py
tests/benchmark1.py
tests/py4j_callback_example.py
tests/py4j_callback_example2.py
tests/py4j_callback_listener_example.py
tests/py4j_example.py
tests/run.py
tests/java/classes/p1/AnObject$InternalClass.class
tests/java/classes/p1/AnObject.class
tests/java/classes/p1/AnObject2.class
tests/java/classes/p1/AnObject3.class
tests/java/classes/p1/AnObject4.class
tests/java/classes/p1/Cat$SmallCat.class
tests/java/classes/p1/Cat.class
tests/java/classes/p1/p2/Animal.class
tests/java/classes/py4j/Base64.class
tests/java/classes/py4j/Base64Test.class
tests/java/classes/py4j/BufferGatewayTest.class
tests/java/classes/py4j/CallbackClient$1.class
tests/java/classes/py4j/CallbackClient.class
tests/java/classes/py4j/CallbackConnection.class
tests/java/classes/py4j/ClientServer$1.class
tests/java/classes/py4j/ClientServer$ClientServerBuilder.class
tests/java/classes/py4j/ClientServer.class
tests/java/classes/py4j/ClientServerConnection.class
tests/java/classes/py4j/ClientServerTest.class
tests/java/classes/py4j/DefaultApplication.class
tests/java/classes/py4j/DefaultGatewayServerListener.class
tests/java/classes/py4j/EchoClient.class
tests/java/classes/py4j/EchoClientTest.class
tests/java/classes/py4j/EchoServer$1.class
tests/java/classes/py4j/EchoServer$2.class
tests/java/classes/py4j/EchoServer.class
tests/java/classes/py4j/EchoServerTest.class
tests/java/classes/py4j/Gateway.class
tests/java/classes/py4j/GatewayConnection.class
